{
	"name": "Thanos",
	"type": "dark",
	"colors": {
		"activityBar.background": "#161719",
		"activityBar.border": "#333333",
		"badge.background": "#ffbf00",
		"badge.foreground": "#000000",
		"editor.background": "#0f0f0f",
		"editor.foreground": "#c5c8c6",
		"editor.lineHighlightBackground": "#282a2e",
		"editor.selectionBackground": "#373b41",
		"editorCursor.foreground": "#c5c8c6",
		"editorError.foreground": "#d13b2e",
		"editorGroup.emptyBackground": "#161719",
		"editorGroupHeader.tabsBackground": "#161719",
		"editorGutter.addedBackground": "#b5bd68",
		"editorGutter.background": "#151515",
		"editorGutter.deletedBackground": "#cc6666",
		"editorGutter.modifiedBackground": "#de935f",
		"editorIndentGuide.background": "#282a2e",
		"editorLink.activeForeground": "#81a2be",
		"editorSuggestWidget.selectedBackground": "#1d1f21",
		"editorWarning.foreground": "#de935f",
		"editorWhitespace.foreground": "#626466",
		"gitDecoration.conflictingResourceForeground": "#6494ed",
		"gitDecoration.deletedResourceForeground": "#ff6347",
		"gitDecoration.ignoredResourceForeground": "#696d71",
		"gitDecoration.modifiedResourceForeground": "#e2c08d",
		"gitDecoration.untrackedResourceForeground": "#73c990",
		"list.activeSelectionBackground": "#222426",
		"list.activeSelectionForeground": "#d9dbde",
		"list.errorForeground": "#d13b2e",
		"list.focusBackground": "#222426",
		"list.focusForeground": "#d9dbde",
		"list.hoverBackground": "#222426",
		"list.inactiveSelectionBackground": "#222426",
		"list.inactiveSelectionForeground": "#d9dbde",
		"list.warningForeground": "#de935f",
		"minimap.background": "#151515",
		"panel.background": "#222222",
		"panel.border": "#333333",
		"peekView.border": "#81a2be",
		"peekViewEditor.background": "#161719",
		"peekViewTitle.background": "#161719",
		"quickInput.background": "#161719",
		"quickInput.foreground": "#a3a8ae",
		"sideBar.background": "#121212",
		"sideBar.border": "#333333",
		"sideBar.foreground": "#a3a8ae",
		"statusBar.background": "#161719",
		"statusBar.foreground": "#c5c8c6",
		"tab.activeBackground": "#030303",
		"tab.activeBorder": "#fd2600",
		"tab.inactiveBackground": "#161719",
		"terminal.background": "#121212",
	},
	"tokenColors": [
		{
			"scope": "meta.class",
			"settings": {
				"foreground": "#C5C8C6"
			}
		},
		{
			"scope": "variable.parameter.function",
			"settings": {
				"foreground": "#C5C8C6"
			}
		},
		{
			"scope": [
				"comment",
				"punctuation.definition.comment"
			],
			"settings": {
				"foreground": "#969896",
				"fontStyle": "italic"
			}
		},
		{
			"scope": [
				"punctuation.definition.variable",
				"punctuation.definition.parameters",
				"punctuation.definition.array",
				"punctuation.definition.block",
				"punctuation.separator",
				"punctuation.accessor",
				"meta.template.expression",
				"meta.array.literal",
				"storage.type.function.arrow"
			],
			"settings": {
				"foreground": "#C5C8C6"
			}
		},
		{
			"scope": "none",
			"settings": {
				"foreground": "#C5C8C6"
			}
		},
		{
			"scope": "keyword.operator",
			"settings": {
				"foreground": "#C5C8C6"
			}
		},
		{
			"scope": "keyword",
			"settings": {
				"foreground": "#B294BB"
			}
		},
		{
			"scope": "meta.decorator",
			"settings": {
				"foreground": "#C5C8C6"
			}
		},
		{
			"scope": [
				"variable",
				"support.variable",
				"support.type.property-name",
				"entity.name.variable"
			],
			"settings": {
				"foreground": "#CC6666"
			}
		},
		{
			"scope": [
				"meta.object-literal.key"
			],
			"settings": {
				"foreground": "#C5C8C6"
			}
		},
		{
			"scope": [
				"support.class",
				"entity.name.class",
				"entity.name.type.class"
			],
			"settings": {
				"foreground": "#F0C674"
			}
		},
		{
			"scope": [
				"entity.name.type",
				"storage.type.cs"
			],
			"settings": {
				"foreground": "#F0C674"
			}
		},
		{
			"scope": "support.constant",
			"settings": {
				"foreground": "#F0C674"
			}
		},
		{
			"scope": [
				"support.type.primitive",
				"support.type.builtin",
				"keyword.type"
			],
			"settings": {
				"foreground": "#C5C8C6"
			}
		},
		{
			"scope": "meta.definition.method",
			"settings": {
				"foreground": "#C5C8C6"
			}
		},
		{
			"scope": [
				"meta.function-call",
				"meta.require",
				"variable.language.super",
				"keyword.other.special-method",
				"entity.name.function"
			],
			"settings": {
				"foreground": "#81A2BE"
			}
		},
		{
			"scope": "storage",
			"settings": {
				"foreground": "#B294BB"
			}
		},
		{
			"scope": "support.function",
			"settings": {
				"foreground": "#8ABEB7"
			}
		},
		{
			"scope": [
				"string",
				"punctuation.definition.string",
				"constant.other.symbol",
				"entity.other.inherited-class"
			],
			"settings": {
				"foreground": "#B5BD68"
			}
		},
		{
			"scope": "constant.numeric",
			"settings": {
				"foreground": "#DE935F"
			}
		},
		{
			"scope": "none",
			"settings": {
				"foreground": "#DE935F"
			}
		},
		{
			"scope": "none",
			"settings": {
				"foreground": "#DE935F"
			}
		},
		{
			"scope": "constant",
			"settings": {
				"foreground": "#DE935F"
			}
		},
		{
			"scope": "entity.other.attribute-name",
			"settings": {
				"foreground": "#DE935F",
				"fontStyle": "italic"
			}
		},
		{
			"scope": "entity.name.tag",
			"settings": {
				"foreground": "#CC6666"
			}
		},
		{
			"scope": [
				"entity.other.attribute-name.id"
			],
			"settings": {
				"foreground": "#81A2BE"
			}
		},
		{
			"scope": "meta.selector",
			"settings": {
				"foreground": "#B294BB"
			}
		},
		{
			"scope": "none",
			"settings": {
				"foreground": "#DE935F"
			}
		},
		{
			"scope": "support.type.property-name.css",
			"settings": {
				"foreground": "#C5C8C6"
			}
		},
		{
			"scope": "support.constant.property-value.css",
			"settings": {
				"foreground": "#DE935F"
			}
		},
		{
			"scope": [
				"markup.heading punctuation.definition.heading",
				"entity.name.section"
			],
			"settings": {
				"foreground": "#CC6666",
				"fontStyle": ""
			}
		},
		{
			"scope": "keyword.other.unit",
			"settings": {
				"foreground": "#DE935F"
			}
		},
		{
			"scope": "punctuation.definition.bold",
			"settings": {
				"fontStyle": "bold"
			}
		},
		{
			"scope": "markup.bold",
			"settings": {
				"foreground": "#DE935F",
				"fontStyle": "bold"
			}
		},
		{
			"scope": "punctuation.definition.italic",
			"settings": {
				"fontStyle": "italic"
			}
		},
		{
			"scope": "markup.italic",
			"settings": {
				"foreground": "#B294BB",
				"fontStyle": "italic"
			}
		},
		{
			"scope": [
				"markup.inline.raw",
				"markup.fenced_code.block"
			],
			"settings": {
				"foreground": "#B5BD68"
			}
		},
		{
			"scope": [
				"meta.link",
				"string.other.link"
			],
			"settings": {
				"foreground": "#81A2BE"
			}
		},
		{
			"scope": "string.other.link.title",
			"settings": {
				"foreground": "#8ABEB7"
			}
		},
		{
			"scope": "beginning.punctuation.definition.list",
			"settings": {
				"foreground": "#CC6666"
			}
		},
		{
			"scope": "markup.quote",
			"settings": {
				"foreground": "#969896"
			}
		},
		{
			"scope": "meta.separator",
			"settings": {
				"foreground": "#C5C8C6"
			}
		},
		{
			"scope": "markup.inserted",
			"settings": {
				"foreground": "#B5BD68"
			}
		},
		{
			"scope": "markup.deleted",
			"settings": {
				"foreground": "#CC6666"
			}
		},
		{
			"scope": "markup.changed",
			"settings": {
				"foreground": "#B294BB"
			}
		},
		{
			"scope": "constant.other.color",
			"settings": {
				"foreground": "#8ABEB7"
			}
		},
		{
			"scope": "string.regexp",
			"settings": {
				"foreground": "#8ABEB7"
			}
		},
		{
			"scope": "constant.character.escape",
			"settings": {
				"foreground": "#8ABEB7"
			}
		},
		{
			"scope": [
				"punctuation.section.embedded",
				"variable.interpolation"
			],
			"settings": {
				"foreground": "#A3685A"
			}
		},
		{
			"scope": "invalid.illegal",
			"settings": {
				"foreground": "#FFFFFF"
			}
		},
		{
			"scope": "invalid.broken",
			"settings": {
				"foreground": "#1D1F21"
			}
		},
		{
			"scope": "invalid.deprecated",
			"settings": {
				"foreground": "#FFFFFF"
			}
		},
		{
			"scope": "invalid.unimplemented",
			"settings": {
				"foreground": "#FFFFFF"
			}
		},
		{
			"scope": "token.info-token",
			"settings": {
				"foreground": "#6796E6"
			}
		},
		{
			"scope": "token.warn-token",
			"settings": {
				"foreground": "#CD9731"
			}
		},
		{
			"scope": "token.error-token",
			"settings": {
				"foreground": "#F44747"
			}
		},
		{
			"scope": "token.debug-token",
			"settings": {
				"foreground": "#B267E6"
			}
		}
	]
}